lilt/__init__.py
lilt/api_client.py
lilt/api_response.py
lilt/configuration.py
lilt/exceptions.py
lilt/py.typed
lilt/rest.py
lilt/api/__init__.py
lilt/api/comments_api.py
lilt/api/connectors_api.py
lilt/api/converter_config_api.py
lilt/api/create_api.py
lilt/api/documents_api.py
lilt/api/domains_api.py
lilt/api/files_api.py
lilt/api/jobs_api.py
lilt/api/languages_api.py
lilt/api/lexicon_api.py
lilt/api/memories_api.py
lilt/api/projects_api.py
lilt/api/qa_api.py
lilt/api/root_api.py
lilt/api/segments_api.py
lilt/api/settings_api.py
lilt/api/translate_api.py
lilt/api/webhook_configuration_api.py
lilt/api/workflows_api.py
lilt/models/__init__.py
lilt/models/add_file_label_request.py
lilt/models/annotation.py
lilt/models/api_root.py
lilt/models/assignment_details.py
lilt/models/assignment_error.py
lilt/models/auto_assignment_parameters.py
lilt/models/auto_assignment_response.py
lilt/models/auto_assignment_response_assignments.py
lilt/models/auto_assignment_response_errors.py
lilt/models/bad_request.py
lilt/models/comment.py
lilt/models/comment_body.py
lilt/models/comment_delete_response.py
lilt/models/connector.py
lilt/models/connector_arguments.py
lilt/models/connector_delete_response.py
lilt/models/connector_job.py
lilt/models/converter_config_update_response.py
lilt/models/create_converter_config_parameters.py
lilt/models/create_webhook_options.py
lilt/models/delete_lilt_create_content200_response.py
lilt/models/delete_segment_from_memory_response.py
lilt/models/document_assignment_parameters.py
lilt/models/document_assignment_response.py
lilt/models/document_comments.py
lilt/models/document_delete_response.py
lilt/models/document_done_update_parameters.py
lilt/models/document_done_update_parameters1.py
lilt/models/document_done_update_parameters2.py
lilt/models/document_parameters.py
lilt/models/document_pretranslate_parameters.py
lilt/models/document_pretranslate_response.py
lilt/models/document_pretranslating.py
lilt/models/document_pretranslating_status.py
lilt_python-3.0.2.dist-info/licenses/LICENSE.md
lilt_python-3.0.2.dist-info/METADATA
lilt_python-3.0.2.dist-info/WHEEL
lilt_python-3.0.2.dist-info/top_level.txt
lilt_python-3.0.2.dist-info/RECORD
