Metadata-Version: 2.4
Name: lilt-python
Version: 3.0.2
Summary: Lilt REST API
Home-page: https://github.com/lilt/lilt-python
Author: OpenAPI Generator community
Author-email: team@openapitools.org
License: Lilt Platform Terms and Conditions
Keywords: OpenAPI,OpenAPI-Generator,Lilt REST API
License-File: LICENSE.md
Requires-Dist: urllib3<3.0.0,>=2.1.0
Requires-Dist: python-dateutil>=2.8.2
Requires-Dist: pydantic>=2
Requires-Dist: typing-extensions>=4.7.1
Dynamic: author
Dynamic: author-email
Dynamic: description
Dynamic: description-content-type
Dynamic: home-page
Dynamic: keywords
Dynamic: license
Dynamic: license-file
Dynamic: requires-dist
Dynamic: summary
